bonk/__init__.py
bonk/admin.py
bonk/apps.py
bonk/models.py
bonk/serializers.py
bonk/tasks.py
bonk/tests.py
bonk/urls.py
bonk/views.py
bonk/migrations/__init__.py
bonk-0.7.2.dist-info/LICENSE.txt
bonk-0.7.2.dist-info/METADATA
bonk-0.7.2.dist-info/WHEEL
bonk-0.7.2.dist-info/top_level.txt
bonk-0.7.2.dist-info/zip-safe
bonk-0.7.2.dist-info/RECORD
